love_calculator/__init__.py
love_calculator/core.py
my_love_calculator-1.0.2.dist-info/licenses/LICENSE
my_love_calculator-1.0.2.dist-info/METADATA
my_love_calculator-1.0.2.dist-info/WHEEL
my_love_calculator-1.0.2.dist-info/top_level.txt
my_love_calculator-1.0.2.dist-info/RECORD
