Metadata-Version: 2.4
Name: my-love-calculator
Version: 1.0.2
Summary: A simple Python love calculator game
Author-email: Eldar <eldar@example.com>
License: MIT
Project-URL: Homepage, https://pypi.org/project/my-love-calculator/
Keywords: game,love,calculator,fun
Classifier: Programming Language :: Python :: 3
Classifier: License :: OSI Approved :: MIT License
License-File: LICENSE
Dynamic: license-file
